dotalib_parsers/__init__.py
dotalib_parsers/web/__init__.py
dotalib_parsers/web/base.py
dotalib_parsers/web/cyberscore.py
dotalib_parsers/web/dotabuff.py
dotalib_parsers/web/hawk/__init__.py
dotalib_parsers/web/hawk/livematches.py
dotalib_parsers/web/hawk/match.py
dotalib_parsers/web/hawk/odds.py
dotalib_parsers-0.0.4.dist-info/LICENSE
dotalib_parsers-0.0.4.dist-info/METADATA
dotalib_parsers-0.0.4.dist-info/WHEEL
dotalib_parsers-0.0.4.dist-info/top_level.txt
dotalib_parsers-0.0.4.dist-info/RECORD
