Metadata-Version: 2.1
Name: dotalib-parsers
Version: 0.0.4
Summary: dotalib-parsers
Author-email: classno <classno@gmail.com>
Classifier: Programming Language :: Python :: 3
Classifier: License :: OSI Approved :: MIT License
Classifier: Operating System :: OS Independent
Requires-Python: >=3.7
License-File: LICENSE
Requires-Dist: dotalib
Requires-Dist: beautifulsoup4
